{
  "general": {
    "screen": {
      "width": "",
      "height": ""
    }
  },
  "block": {
    "color": "",
    "textColor": ""
  },
  "easy": {
    "blockFreq": {
    },
    "powerUps": {
      "spring": 40,
      "springBoots": 120,
      "orbBack": 30,
      "orbForward": 35
    },
    "blockTypeFreq": {
      "sideways": 5,
      "rising": 5
    },
    "wordTypeFreq": {
      "spike": 20
    }
  },
  "hard": {
    "blockTypeFreq": {
      "sideways": 5,
      "rising": 5
    },
    "powerUps": {
      "spring": 40,
      "springBoots": 120,
      "orbBack": 30,
      "orbForward": 35
    },
    "blockTypeFreq": {
      "sideways": 5,
      "rising": 5
    },
    "wordTypeFreq": {
      "spike": 5
    }
  }
}